mongo_archviz/__init__.py
mongo_archviz/schema.py
mongo_archviz-1.0.0.dist-info/licenses/LICENSE
mongo_archviz-1.0.0.dist-info/METADATA
mongo_archviz-1.0.0.dist-info/WHEEL
mongo_archviz-1.0.0.dist-info/top_level.txt
mongo_archviz-1.0.0.dist-info/RECORD
