Metadata-Version: 2.4
Name: mongo-archviz
Version: 1.0.0
Summary: A MongoDB schema report generator for visualizing database architecture.
Home-page: https://github.com/rishicarter/mongo-archviz
Author: Rishi Aluri
Author-email: rishialuri@gmail.com
License: MIT
Classifier: Programming Language :: Python :: 3
Classifier: Operating System :: OS Independent
Requires-Python: >=3.6
License-File: LICENSE
Requires-Dist: pymongo>=3.11
Provides-Extra: test
Requires-Dist: mongomock>=3.19; extra == "test"
Dynamic: author
Dynamic: author-email
Dynamic: classifier
Dynamic: description
Dynamic: description-content-type
Dynamic: home-page
Dynamic: license
Dynamic: license-file
Dynamic: provides-extra
Dynamic: requires-dist
Dynamic: requires-python
Dynamic: summary
